{
  "id": "charlotte",
  "displayName": "Charlotte, NC",
  "coverage": {
    "country": "US",
    "region": "NC",
    "city": "Charlotte",
    "zips": ["28202","28203","28204","28205","28206","28207","28208","28209","28210","28211","28212","28213","28214","28215","28216","28217","28226","28227","28244","28262","28269","28270","28273","28277","28278","28280","28281","28282"],
    "aliases": ["charlotte north carolina", "charlotte nc", "queen city", "clt", "mecklenburg county"]
  },
  "source": {
    "name": "City of Charlotte Solid Waste Services",
    "url": "https://charlottenc.gov/Services/Trash-and-Recycling/Collection-Guidelines",
    "generatedAt": "2026-02-27",
    "notes": "Based on official City of Charlotte collection guidelines. Bi-weekly recycling on Green/Orange week schedule. Only plastic bottles and jugs WITH necks accepted (no tubs/clamshells)."
  },
  "materials": [
    {"id":"plastic-bottles","name":"Plastic bottles","aliases":["water bottle","soda bottle","plastic bottle","shampoo bottle","detergent bottle","laundry bottle"],"category":"recycle","instructions":["Empty and rinse","Replace cap","Place in green recycling cart"],"notes":["Charlotte only accepts plastic bottles and jugs with necks","No tubs, cups, clamshells, or trays"],"commonMistakes":["Don't include plastic tubs or containers without necks","Don't include bottles with liquid still inside"],"tags":["plastic","bottle","container"],"examples":["Water bottle","Soda bottle","Shampoo bottle","Laundry detergent bottle"]},
    {"id":"plastic-jugs","name":"Plastic jugs","aliases":["milk jug","juice jug","plastic jug","gallon jug","detergent jug"],"category":"recycle","instructions":["Empty and rinse","Replace cap","Place in green recycling cart"],"notes":["Must have a neck to qualify for Charlotte recycling","Jugs are accepted; tubs are not"],"commonMistakes":["Don't flatten jugs; leave them as-is with cap on"],"tags":["plastic","jug","container"],"examples":["Milk jug","Orange juice jug","Bleach jug"]},
    {"id":"plastic-tubs","name":"Plastic tubs and containers","aliases":["yogurt tub","butter tub","sour cream container","deli container","plastic cup","clamshell","berry container","takeout container"],"category":"trash","instructions":["Place in trash","Charlotte does NOT accept plastic tubs, cups, or clamshells"],"notes":["Only bottles and jugs with necks are recyclable in Charlotte","This is a common source of confusion"],"commonMistakes":["Don't put yogurt tubs in recycling","Don't put clamshells or deli containers in recycling"],"tags":["plastic","container","food"],"examples":["Yogurt tub","Berry clamshell","Deli container","Butter tub"]},
    {"id":"cardboard-small","name":"Cardboard / small boxes","aliases":["cardboard box","shipping box","amazon box","cereal box","shoe box","small box"],"category":"recycle","instructions":["Cut or tear into small pieces that fit in the cart","Remove packing materials","Place in green recycling cart with lid closed"],"notes":["All cardboard must be cut or torn into small pieces","Items must fit with the lid closed"],"commonMistakes":["Don't leave large uncut cardboard; it will not be collected","Remove all packing materials like styrofoam and bubble wrap"],"tags":["paper","cardboard","packaging"],"examples":["Amazon box (cut up)","Cereal box","Shoe box"]},
    {"id":"cardboard-large-uncut","name":"Large uncut cardboard","aliases":["large cardboard","uncut box","big box","furniture box","appliance box"],"category":"trash","instructions":["Cut or tear into small pieces first, then recycle","If too large to fit in cart with lid closed, it will NOT be collected","Break down before placing in recycling cart"],"notes":["Charlotte requires all cardboard to fit inside the cart with the lid closed","Uncut large cardboard left beside the cart will be rejected"],"commonMistakes":["Don't leave large cardboard next to the cart; it won't be picked up","Always cut or tear into manageable pieces"],"tags":["paper","cardboard","packaging"],"examples":["TV box left whole","Furniture box not broken down"]},
    {"id":"paper","name":"Paper and magazines","aliases":["paper","office paper","junk mail","magazine","mail","printer paper","notebook paper","newspaper","envelopes"],"category":"recycle","instructions":["Place loose in green recycling cart","No need to remove staples or window envelopes"],"notes":["Must be dry and clean","Do not bag paper in plastic bags"],"commonMistakes":["Don't include shredded paper; it clogs machinery","Don't include wet or food-soiled paper"],"tags":["paper","office","magazine"],"examples":["Junk mail","Magazine","Newspaper","Office paper"]},
    {"id":"shredded-paper","name":"Shredded paper","aliases":["shredded paper","paper shreds","cross-cut paper"],"category":"trash","instructions":["Place in trash","Charlotte does NOT accept shredded paper in recycling"],"notes":["Shredded paper clogs recycling equipment and is too small to sort","Consider composting at home if possible"],"commonMistakes":["Don't put shredded paper in the green recycling cart","Don't bag shredded paper and put it in recycling"],"tags":["paper","office"],"examples":["Shredded documents","Cross-cut paper shreds"]},
    {"id":"milk-cartons","name":"Milk / juice cartons","aliases":["milk carton","juice carton","juice box","tetra pak","drink carton","broth carton"],"category":"recycle","instructions":["Empty and rinse","Place in green recycling cart"],"notes":["Cartons are accepted in Charlotte curbside recycling"],"commonMistakes":["Don't include cartons with liquid still inside"],"tags":["paper","carton","beverage"],"examples":["Milk carton","Juice box","Broth carton"]},
    {"id":"glass-bottles","name":"Glass bottles and jars","aliases":["glass bottle","glass jar","wine bottle","beer bottle","sauce jar","pickle jar","mason jar"],"category":"recycle","instructions":["Empty and rinse","Lids can stay on","Place in green recycling cart"],"notes":["Charlotte accepts glass in curbside recycling","Lids do not need to be removed"],"commonMistakes":["Don't include broken glass; wrap and trash it","Don't include window glass, mirrors, or ceramics"],"tags":["glass","bottle","jar"],"examples":["Wine bottle","Beer bottle","Pasta sauce jar","Pickle jar"]},
    {"id":"metal-cans","name":"Empty metal cans","aliases":["aluminum can","soda can","beer can","tin can","steel can","soup can","food can"],"category":"recycle","instructions":["Empty and rinse","Place in green recycling cart"],"notes":["Labels can stay on","Includes aluminum and steel/tin cans"],"commonMistakes":["Don't include cans with food residue","Don't crush cans; leave them as-is"],"tags":["metal","can","container"],"examples":["Soda can","Beer can","Soup can","Tuna can"]},
    {"id":"aluminum-foil","name":"Aluminum foil","aliases":["aluminum foil","tin foil","foil"],"category":"recycle","instructions":["Clean off all food residue","Ball up into a ball at least 2 inches wide","Place in green recycling cart"],"notes":["Must be clean; heavily soiled foil goes in trash"],"commonMistakes":["Don't recycle foil with baked-on food","Small pieces get lost; ball them together"],"tags":["metal","aluminum","kitchen"],"examples":["Clean foil sheets","Foil pie pan"]},
    {"id":"aerosol-cans","name":"Aerosol cans","aliases":["aerosol","spray can","hairspray can","spray paint can"],"category":"recycle","instructions":["Must be completely empty","Place in green recycling cart"],"notes":["Non-empty aerosol cans are hazardous waste"],"commonMistakes":["Don't recycle if can still has pressure or product"],"tags":["metal","container","pressurized"],"examples":["Hairspray can","Cooking spray can","Compressed air can"]},
    {"id":"plastic-bags","name":"Plastic bags","aliases":["grocery bag","shopping bag","plastic film","produce bag","bread bag","zip-lock bag","dry cleaning bag"],"category":"trash","instructions":["Do NOT put in green recycling cart","Take to Harris Teeter, Walmart, or Target for store drop-off","Otherwise place in trash"],"notes":["Plastic bags jam Charlotte's recycling machinery","Most grocery stores in Charlotte accept bags for recycling"],"commonMistakes":["Never bag recyclables in plastic bags","Never put film plastic in the green cart"],"tags":["plastic","bag","film"],"examples":["Harris Teeter bag","Grocery bag","Produce bag"]},
    {"id":"styrofoam","name":"Styrofoam","aliases":["styrofoam","polystyrene","foam cup","foam container","packing peanuts","foam tray","eps"],"category":"trash","instructions":["Place in trash","Not accepted in Charlotte recycling"],"notes":["Styrofoam is not recyclable curbside in Charlotte"],"commonMistakes":["Don't put styrofoam in the green recycling cart"],"tags":["plastic","foam","packaging"],"examples":["Foam cup","Foam takeout box","Packing peanuts","Meat tray"]},
    {"id":"food-waste","name":"Food waste","aliases":["food scraps","food waste","leftovers","spoiled food","fruit scraps","vegetable scraps"],"category":"trash","instructions":["Place in trash","Charlotte does not offer curbside composting"],"notes":["No curbside composting program available in Charlotte","Consider backyard composting for food scraps"],"commonMistakes":["Don't put food waste in the green recycling cart"],"tags":["organic","food"],"examples":["Banana peel","Leftover food","Spoiled vegetables"]},
    {"id":"yard-waste","name":"Yard waste","aliases":["grass clippings","leaves","branches","garden waste","lawn clippings","tree trimmings"],"category":"trash","instructions":["Place in brown paper yard waste bags or an unlidded container marked 'yard waste'","Branches must be cut to 4 feet or shorter and bundled","Set out on your regular collection day"],"notes":["Charlotte collects yard waste separately from trash","Do not use plastic bags for yard waste"],"commonMistakes":["Don't bag yard waste in plastic bags","Don't put in the green recycling cart"],"tags":["organic","yard","garden"],"examples":["Grass clippings","Leaves","Small branches"]},
    {"id":"paper-plates","name":"Paper plates and napkins","aliases":["paper plate","paper napkin","paper towel","used napkin","used paper towel"],"category":"trash","instructions":["Place in trash","Not recyclable when soiled with food"],"notes":["Food-contaminated paper products are not accepted in Charlotte recycling"],"commonMistakes":["Don't put food-soiled paper in the green recycling cart"],"tags":["paper","food","disposable"],"examples":["Used paper plate","Dirty napkin","Used paper towel"]},
    {"id":"takeout-containers","name":"Takeout containers","aliases":["takeout container","to-go container","foam takeout","plastic takeout","restaurant container"],"category":"trash","instructions":["Place in trash","Not accepted in Charlotte recycling"],"notes":["Takeout containers are typically food-soiled and made of non-recyclable materials in Charlotte"],"commonMistakes":["Don't put in green recycling cart even if rinsed"],"tags":["food","container","disposable"],"examples":["Foam clamshell","Plastic to-go box","Chinese food container"]},
    {"id":"plasticware","name":"Plastic utensils and cups","aliases":["plastic fork","plastic spoon","plastic knife","plasticware","plastic cup","solo cup","red cup","plastic straw"],"category":"trash","instructions":["Place in trash","Not recyclable in Charlotte"],"notes":["Plastic utensils and cups are not accepted in Charlotte recycling"],"commonMistakes":["Don't put plastic utensils in the green recycling cart"],"tags":["plastic","disposable","food"],"examples":["Plastic fork","Solo cup","Plastic straw"]},
    {"id":"food-trays","name":"Plastic food trays","aliases":["food tray","meat tray","produce tray","plastic tray","black plastic tray"],"category":"trash","instructions":["Place in trash","Charlotte does not accept plastic food trays"],"notes":["Only bottles and jugs with necks are recyclable plastic in Charlotte"],"commonMistakes":["Don't put food trays in the green recycling cart"],"tags":["plastic","food","container"],"examples":["Styrofoam meat tray","Black plastic deli tray","Produce tray"]},
    {"id":"diapers","name":"Diapers","aliases":["diaper","disposable diaper","baby diaper","adult diaper"],"category":"trash","instructions":["Bag and place in trash"],"notes":["Not recyclable or compostable"],"commonMistakes":["Never put diapers in the green recycling cart"],"tags":["hygiene","household"],"examples":["Disposable baby diaper","Adult incontinence product"]},
    {"id":"hoses-cords","name":"Hoses and cords","aliases":["garden hose","extension cord","power cord","hose","rope","cable","wire"],"category":"trash","instructions":["Place in trash","Do NOT put in green recycling cart"],"notes":["Hoses and cords tangle in recycling machinery and shut down the sorting facility"],"commonMistakes":["Never put hoses, cords, or cables in recycling"],"tags":["household","garden"],"examples":["Garden hose","Extension cord","Rope"]},
    {"id":"batteries","name":"Batteries","aliases":["battery","AA battery","AAA battery","lithium battery","rechargeable battery","9V battery","car battery"],"category":"hazardous","instructions":["Do not put in trash or recycling","Take to Mecklenburg County Household Hazardous Waste collection","Tape terminals of lithium and 9V batteries before transport"],"notes":["Batteries cause fires in recycling trucks","Mecklenburg County holds periodic hazardous waste collection events"],"commonMistakes":["Don't throw batteries in trash or recycling"],"tags":["hazardous","battery","electronics"],"examples":["AA batteries","Laptop battery","Car battery"]},
    {"id":"electronics","name":"Electronics / E-waste","aliases":["e-waste","computer","laptop","phone","smartphone","tablet","TV","television","monitor","printer"],"category":"dropoff","instructions":["Take to Mecklenburg County recycling centers","Best Buy accepts many electronics for free","Delete personal data before disposal"],"notes":["North Carolina law prohibits putting electronics in the trash"],"commonMistakes":["Don't put electronics in trash or recycling cart"],"tags":["electronics","e-waste"],"examples":["Old laptop","Broken phone","TV","Printer"]},
    {"id":"paint","name":"Paint","aliases":["latex paint","oil paint","house paint","spray paint","paint can"],"category":"hazardous","instructions":["Take to Mecklenburg County Household Hazardous Waste collection","Latex paint: can also dry out with kitty litter and trash the solid","Oil-based paint: must go to hazardous waste"],"notes":["Mecklenburg County holds HHW events for Charlotte residents"],"commonMistakes":["Don't pour paint down the drain"],"tags":["hazardous","chemical","household"],"examples":["Latex wall paint","Oil-based stain","Spray paint"]},
    {"id":"motor-oil","name":"Motor oil","aliases":["used oil","engine oil","automotive oil","transmission fluid"],"category":"hazardous","instructions":["Take to Mecklenburg County recycling center","AutoZone and O'Reilly in Charlotte also accept used oil"],"notes":["Most auto parts stores accept oil for free"],"commonMistakes":["Don't pour down drains or into storm drains"],"tags":["hazardous","automotive"],"examples":["Used engine oil","Transmission fluid"]},
    {"id":"medications","name":"Medications","aliases":["medicine","pills","prescription drugs","expired medicine","over-the-counter medicine"],"category":"dropoff","instructions":["Take to Charlotte-area drug take-back locations","CVS and Walgreens in Charlotte participate in take-back programs","If no drop-off: mix with coffee grounds, seal in bag, and trash"],"notes":["Charlotte-Mecklenburg Police holds periodic drug take-back events"],"commonMistakes":["Don't flush medications down the toilet"],"tags":["pharmaceutical","household"],"examples":["Expired pills","Old prescriptions","Unused antibiotics"]},
    {"id":"clothing","name":"Clothing and textiles","aliases":["clothes","old clothes","shoes","sneakers","textiles","fabric"],"category":"dropoff","instructions":["Donate to Goodwill, Salvation Army, or local Charlotte thrift stores","Textile recycling bins at various Charlotte locations","Even worn-out textiles are accepted in textile bins"],"notes":["Charlotte has many donation and textile recycling options"],"commonMistakes":["Don't put clothing in the green recycling cart"],"tags":["textile","clothing","donation"],"examples":["Old t-shirt","Worn jeans","Old sneakers"]},
    {"id":"light-bulbs","name":"Light bulbs","aliases":["light bulb","CFL","fluorescent bulb","LED bulb","incandescent bulb"],"category":"hazardous","instructions":["CFL and fluorescent: take to Mecklenburg County HHW or Home Depot/Lowe's","LED bulbs: e-waste recycling","Incandescent: wrap and place in trash"],"notes":["CFL bulbs contain mercury and require special handling"],"commonMistakes":["Don't put CFL or fluorescent bulbs in trash"],"tags":["hazardous","lighting"],"examples":["CFL bulb","Fluorescent tube","LED bulb"]},
    {"id":"books","name":"Books","aliases":["book","paperback","hardcover","textbook","novel"],"category":"recycle","instructions":["Donate if in good condition","If damaged, place in green recycling cart","Remove hardcover bindings with glossy laminate (trash those)"],"notes":["Charlotte-Mecklenburg Library accepts book donations","Donating is always preferred over recycling"],"commonMistakes":["Don't throw usable books in the trash"],"tags":["paper","book","donation"],"examples":["Paperback novel","Textbook","Cookbook"]},
    {"id":"coffee-cups","name":"Disposable coffee cups","aliases":["coffee cup","paper cup","starbucks cup","to-go cup"],"category":"trash","instructions":["Place in trash","Plastic-lined paper cups are not recyclable in Charlotte"],"notes":["The plastic lining prevents recycling","Plastic lids: also trash in Charlotte"],"commonMistakes":["Don't put lined cups in the green recycling cart"],"tags":["paper","beverage","disposable"],"examples":["Starbucks cup","Dunkin' cup"]},
    {"id":"receipts","name":"Receipts","aliases":["receipt","store receipt","thermal receipt"],"category":"trash","instructions":["Place in trash","Thermal paper contains BPA and contaminates recycling"],"notes":["Thermal receipts are not recyclable"],"commonMistakes":["Don't put receipts in the green recycling cart"],"tags":["paper","thermal"],"examples":["Harris Teeter receipt","CVS receipt"]},
    {"id":"candy-wrapper","name":"Candy wrappers","aliases":["candy wrapper","chocolate wrapper","candy bar wrapper","snack wrapper"],"category":"trash","instructions":["Place in trash","Metallized plastic film is not recyclable"],"notes":["Wrappers look metallic but are multi-layer plastic"],"commonMistakes":["Don't put in recycling"],"tags":["plastic","film","wrapper"],"examples":["Snickers wrapper","M&M bag","Kit Kat wrapper"]},
    {"id":"chip-bag","name":"Chip bags / snack bags","aliases":["chip bag","doritos bag","lays bag","snack bag","popcorn bag"],"category":"trash","instructions":["Place in trash","Metallized film; not recyclable in Charlotte"],"notes":["The shiny interior is aluminum bonded to plastic"],"commonMistakes":["Don't put in recycling"],"tags":["plastic","film","snack"],"examples":["Doritos bag","Lay's bag","Cheetos bag"]},
    {"id":"pizza-box","name":"Pizza box","aliases":["pizza box","pizza cardboard"],"category":"trash","instructions":["If heavily soiled with grease: place in trash","If clean (top half): tear off clean portion and recycle that part"],"notes":["Food-soiled cardboard is not accepted in Charlotte recycling","Charlotte has no curbside composting to handle greasy paper"],"commonMistakes":["Don't put grease-soaked cardboard in the green recycling cart"],"tags":["paper","cardboard","food"],"examples":["Greasy pizza box","Domino's box"]},
    {"id":"bubble-wrap","name":"Bubble wrap / packing materials","aliases":["bubble wrap","air pillows","packing material","packing peanuts"],"category":"trash","instructions":["Place in trash","Or take plastic film to store drop-off bins"],"notes":["Plastic film is not accepted in Charlotte curbside recycling"],"commonMistakes":["Don't put in the green recycling cart"],"tags":["plastic","film","packaging"],"examples":["Bubble wrap","Air pillows","Packing peanuts"]},
    {"id":"cereal-box","name":"Cereal box / paperboard","aliases":["cereal box","cracker box","food box","pasta box","paperboard"],"category":"recycle","instructions":["Flatten","Remove plastic liner bag (trash it)","Tear or cut to fit in green recycling cart"],"notes":["Thin paperboard is recyclable in Charlotte"],"commonMistakes":["Don't forget to remove the plastic liner"],"tags":["paper","cardboard","food"],"examples":["Cheerios box","Pasta box","Cracker box"]},
    {"id":"fast-food-wrapper","name":"Fast food wrappers","aliases":["fast food wrapper","burger wrapper","taco wrapper","sandwich wrapper"],"category":"trash","instructions":["Place in trash","Food-soiled paper is not recyclable in Charlotte"],"notes":["Charlotte has no curbside composting for food-soiled paper"],"commonMistakes":["Don't put greasy wrappers in the green recycling cart"],"tags":["paper","food","wrapper"],"examples":["Bojangles wrapper","Chick-fil-A wrapper","McDonald's wrapper"]},
    {"id":"cooking-oil","name":"Cooking oil / grease","aliases":["cooking oil","grease","frying oil","vegetable oil","bacon grease"],"category":"dropoff","instructions":["Collect in a sealed container","Take to Mecklenburg County recycling center","Never pour down the drain"],"notes":["Grease causes sewer blockages"],"commonMistakes":["Don't pour down sink or storm drains"],"tags":["organic","oil"],"examples":["Used frying oil","Bacon grease"]},
    {"id":"propane-tanks","name":"Propane tanks","aliases":["propane tank","propane cylinder","camping propane","grill tank"],"category":"hazardous","instructions":["Take to Mecklenburg County Household Hazardous Waste facility","Never put in trash or recycling"],"notes":["Pressurized containers are fire and explosion risks"],"commonMistakes":["Never puncture or put in trash"],"tags":["hazardous","pressurized"],"examples":["BBQ propane tank","Camping propane canister"]},
    {"id":"sharps","name":"Needles / sharps","aliases":["needle","syringe","sharps","lancet"],"category":"hazardous","instructions":["Place in puncture-resistant sharps container","Take to Mecklenburg County HHW or check with your pharmacy"],"notes":["Never place loose sharps in trash or recycling"],"commonMistakes":["Never put loose sharps in trash"],"tags":["medical","hazardous"],"examples":["Insulin needles","Lancets"]},
    {"id":"mattress","name":"Mattress","aliases":["mattress","box spring","bed mattress"],"category":"dropoff","instructions":["Schedule a bulk pickup through Charlotte 311 or CLTplus app","Or take to a Mecklenburg County full-service recycling center"],"notes":["Charlotte offers bulk item pickup by request"],"commonMistakes":["Don't leave at curb without scheduling"],"tags":["furniture","bulk"],"examples":["Old mattress","Box spring"]},
    {"id":"large-items","name":"Large / bulk items","aliases":["furniture","couch","sofa","large item","bulk item","appliance"],"category":"dropoff","instructions":["Schedule bulk pickup through Charlotte 311 or CLTplus app","Place at curb on scheduled day"],"notes":["Charlotte offers scheduled bulk pickups"],"commonMistakes":["Don't leave at curb without scheduling"],"tags":["furniture","bulk"],"examples":["Old couch","Broken dresser","Worn-out recliner"]},
    {"id":"chargers-cables","name":"Chargers and cables","aliases":["charger","cable","usb cable","phone charger","extension cord","power cord","hdmi cable"],"category":"dropoff","instructions":["Take to Best Buy or Mecklenburg County recycling center","Do NOT put in green recycling cart"],"notes":["Cables tangle in recycling machinery"],"commonMistakes":["Never put cables in curbside recycling"],"tags":["electronics","e-waste"],"examples":["iPhone charger","USB cable","Extension cord"]},
    {"id":"smartphone","name":"Smartphone / phone","aliases":["phone","smartphone","iphone","android phone","cell phone","old phone"],"category":"dropoff","instructions":["Factory reset and wipe data first","Trade in at carrier stores or Apple/Samsung","Take to Best Buy for free recycling"],"notes":["NC law prohibits electronics in trash"],"commonMistakes":["Don't forget to wipe personal data"],"tags":["electronics","e-waste","battery"],"examples":["Old iPhone","Broken Samsung","Old Android phone"]},
    {"id":"fruit","name":"Fruit / fruit scraps","aliases":["fruit","apple","banana","orange","grapes","strawberry","watermelon","peach","mango","avocado","lemon"],"category":"trash","instructions":["Place in trash","Charlotte does not have curbside composting"],"notes":["Consider backyard composting if possible"],"commonMistakes":["Don't put food waste in the green recycling cart"],"tags":["organic","food","fruit"],"examples":["Banana peel","Apple core","Orange peel"]},
    {"id":"vegetables","name":"Vegetables / vegetable scraps","aliases":["vegetable","vegetables","carrot","broccoli","lettuce","onion","potato","corn","cucumber"],"category":"trash","instructions":["Place in trash","No curbside composting in Charlotte"],"notes":["Consider backyard composting"],"commonMistakes":["Don't put food waste in recycling"],"tags":["organic","food","vegetable"],"examples":["Carrot peels","Broccoli stems","Potato peels"]},
    {"id":"meat-bones","name":"Meat and bones","aliases":["meat","chicken","beef","steak","pork","fish","bones","bacon","turkey"],"category":"trash","instructions":["Bag and place in trash"],"notes":["Charlotte does not have curbside composting"],"commonMistakes":["Don't put meat or bones in recycling"],"tags":["organic","food","meat"],"examples":["Chicken bones","Steak trimmings","Fish scraps"]},
    {"id":"dairy","name":"Dairy products","aliases":["dairy","milk","cheese","yogurt","butter","cream","ice cream","sour cream"],"category":"trash","instructions":["Pour expired liquids down drain","Solid dairy products in trash","Rinse and recycle containers separately"],"notes":["No curbside composting in Charlotte"],"commonMistakes":["Rinse the container before recycling it"],"tags":["organic","food","dairy"],"examples":["Expired milk","Old cheese","Spoiled yogurt"]},
    {"id":"coffee-grounds","name":"Coffee grounds / tea bags","aliases":["coffee grounds","coffee filter","tea bag","tea bags","used coffee"],"category":"trash","instructions":["Place in trash","Charlotte does not have curbside composting"],"notes":["Consider backyard composting"],"commonMistakes":["Don't put in the green recycling cart"],"tags":["organic","food","beverage"],"examples":["Used coffee grounds","Coffee filter","Tea bags"]},
    {"id":"pet-waste","name":"Pet waste","aliases":["pet waste","dog poop","cat litter","kitty litter"],"category":"trash","instructions":["Bag and place in trash"],"notes":["Pet waste contains harmful bacteria"],"commonMistakes":["Never compost pet waste","Don't flush cat litter"],"tags":["organic","pet"],"examples":["Dog waste bag","Used cat litter"]},
    {"id":"wax-paper","name":"Wax paper / parchment paper","aliases":["wax paper","parchment paper","baking paper"],"category":"trash","instructions":["Place in trash","Not recyclable due to wax/silicone coating"],"notes":["Charlotte does not have curbside composting for these items"],"commonMistakes":["Don't put in the green recycling cart"],"tags":["paper","kitchen"],"examples":["Wax paper","Parchment paper"]},
    {"id":"mirrors","name":"Mirrors","aliases":["mirror","broken mirror","wall mirror"],"category":"trash","instructions":["Wrap carefully and place in trash","Label bag as 'BROKEN GLASS' if applicable"],"notes":["Metallic coating prevents glass recycling"],"commonMistakes":["Never put mirrors in recycling"],"tags":["glass","household"],"examples":["Bathroom mirror","Broken mirror"]},
    {"id":"ceramics","name":"Ceramics and pottery","aliases":["ceramic","pottery","mug","plate","bowl","porcelain"],"category":"trash","instructions":["Place in trash","Ceramics are not recyclable"],"notes":["Ceramics contaminate glass recycling"],"commonMistakes":["Don't put ceramics or broken dishes in recycling"],"tags":["household","kitchen"],"examples":["Broken mug","Old dinner plate","Ceramic bowl"]},
    {"id":"ink-cartridges","name":"Ink / toner cartridges","aliases":["ink cartridge","toner cartridge","printer cartridge"],"category":"dropoff","instructions":["Return to Staples or Office Depot","Manufacturers offer mail-back programs"],"notes":["Some stores give credit for cartridge returns"],"commonMistakes":["Don't throw in trash"],"tags":["electronics","office"],"examples":["HP ink cartridge","Canon toner"]},
    {"id":"fluorescent-tubes","name":"Fluorescent tubes","aliases":["fluorescent tube","fluorescent light","CFL bulb"],"category":"hazardous","instructions":["Take to Mecklenburg County HHW or Home Depot/Lowe's","Handle carefully to avoid breakage"],"notes":["Contains mercury; requires special handling"],"commonMistakes":["Don't put in trash or recycling","Don't break them"],"tags":["hazardous","lighting","mercury"],"examples":["4-foot fluorescent tube","CFL bulb"]},
    {"id":"tires","name":"Tires","aliases":["tire","car tire","bicycle tire"],"category":"dropoff","instructions":["Take to tire retailer or Mecklenburg County recycling center"],"notes":["Most shops accept old tires when you buy new ones"],"commonMistakes":["Don't dump illegally"],"tags":["automotive","rubber"],"examples":["Car tire","Bicycle tire"]},
    {"id":"toothbrush","name":"Toothbrush","aliases":["toothbrush","electric toothbrush head","manual toothbrush"],"category":"trash","instructions":["Place in trash"],"notes":["Mixed plastic; not recyclable curbside"],"commonMistakes":["Don't put in recycling"],"tags":["plastic","hygiene"],"examples":["Manual toothbrush","Electric toothbrush head"]},
    {"id":"cosmetics","name":"Makeup / cosmetics","aliases":["makeup","lipstick","mascara","cosmetics","nail polish"],"category":"trash","instructions":["Most containers go in trash","Check brand take-back programs for recycling options"],"notes":["Small items fall through sorting screens at recycling facilities"],"commonMistakes":["Nail polish is hazardous; take to HHW if possible"],"tags":["plastic","beauty"],"examples":["Lipstick tube","Mascara","Foundation bottle"]},
    {"id":"egg-carton","name":"Egg cartons","aliases":["egg carton","dozen eggs carton"],"category":"recycle","instructions":["Paper/cardboard egg cartons: place in green recycling cart","Styrofoam egg cartons: place in trash"],"notes":["Only paper-based cartons are recyclable"],"commonMistakes":["Don't recycle styrofoam egg cartons"],"tags":["paper","cardboard","food"],"examples":["Paper egg carton","Cardboard egg carton"]},
    {"id":"metal-lids","name":"Metal lids and caps","aliases":["metal lid","bottle cap","jar lid","metal cap"],"category":"recycle","instructions":["Leave lids on glass jars","Loose metal lids: place inside a metal can and crimp the top to contain them","Place in green recycling cart"],"notes":["Small loose lids can fall through sorting screens"],"commonMistakes":["Don't put loose small caps in recycling; contain them in a can"],"tags":["metal","container"],"examples":["Jar lid","Metal bottle cap"]},
    {"id":"paper-bags","name":"Paper bags","aliases":["paper bag","kraft bag","lunch bag","brown bag"],"category":"recycle","instructions":["Flatten and place in green recycling cart"],"notes":["Clean paper bags are recyclable"],"commonMistakes":["Don't recycle paper bags soiled with food"],"tags":["paper","bag"],"examples":["Brown grocery bag","Paper lunch bag"]},
    {"id":"wrapping-paper","name":"Wrapping paper","aliases":["wrapping paper","gift wrap","tissue paper"],"category":"trash","instructions":["Most wrapping paper goes in trash due to glitter, foil, or plastic lamination","Plain paper wrapping (no glitter/foil): can be recycled"],"notes":["Do the scrunch test: if it stays scrunched it may be recyclable"],"commonMistakes":["Don't assume all wrapping paper is recyclable"],"tags":["paper","holiday"],"examples":["Glossy gift wrap","Metallic wrapping paper","Plain kraft wrapping paper (recyclable)"]},
    {"id":"cleaning-chemicals","name":"Cleaning products / chemicals","aliases":["bleach","cleaning spray","household chemicals","oven cleaner","drain cleaner"],"category":"hazardous","instructions":["Take to Mecklenburg County Household Hazardous Waste collection","Empty containers that held non-hazardous cleaners: rinse and recycle if #1 or #2 plastic bottle"],"notes":["Never mix chemicals together"],"commonMistakes":["Don't pour chemicals down drains","Don't put partially full containers in trash"],"tags":["hazardous","chemical","household"],"examples":["Oven cleaner","Drain cleaner","Bleach bottle (empty = recycle; full = HHW)"]}
  ],
  "rulesSummary": {
    "accepted": {
      "recycle": ["Cardboard and small boxes (cut or torn into small pieces)","Plastic bottles and jugs with necks","Paper and magazines","Milk/juice cartons","Glass bottles and jars (lids can stay on)","Empty metal cans (aluminum and steel)","Aluminum foil (clean)","Aerosol cans (empty)","Paper egg cartons","Books and paperboard boxes"],
      "trash": ["All food waste (no curbside composting)","Plastic tubs, cups, clamshells, and trays","Styrofoam","Plastic bags and film","Shredded paper","Paper plates, napkins, paper towels","Takeout containers","Diapers","Coffee cups with plastic lining","Candy/chip wrappers"]
    },
    "notAccepted": {
      "recycle": ["Large uncut cardboard that won't fit in cart","Food or liquids in containers","Shredded paper","Paper plates and napkins","Plastic bags, food trays, cups, and plasticware","Takeout containers","Styrofoam","Diapers","Hoses and cords","Ceramics and mirrors"]
    },
    "tips": ["Recycling is collected bi-weekly on your Green or Orange week schedule","Check your schedule with the My Charlotte Lookup tool","Cart must be within 6 feet of the curb by 6 AM on collection day","All items must fit in the cart with the lid closed","Only plastic bottles and jugs WITH necks are recyclable (no tubs, cups, or clamshells)","Cut or tear all cardboard into small pieces before recycling","Charlotte has NO curbside composting program"]
  },
  "locations": [
    {"name":"Foxhole Recycling Center","address":"5150 Beatties Ford Rd, Charlotte, NC 28216","phone":"311","url":"https://charlottenc.gov/Services/Trash-and-Recycling","accepts":["Cardboard","Paper","Plastic bottles","Glass","Metal cans","Electronics"],"hours":"Tuesday-Saturday 7am-4pm","notes":"Full-service Mecklenburg County recycling center."},
    {"name":"Hickory Grove Recycling Center","address":"8403 Fairview Rd, Charlotte, NC 28227","phone":"311","url":"https://charlottenc.gov/Services/Trash-and-Recycling","accepts":["Cardboard","Paper","Plastic bottles","Glass","Metal cans","Electronics"],"hours":"Tuesday-Saturday 7am-4pm","notes":"Full-service Mecklenburg County recycling center."},
    {"name":"Mecklenburg County HHW Facility","address":"11220 Statesville Rd, Charlotte, NC 28269","phone":"980-314-3980","url":"https://www.mecknc.gov/LUESA/SolidWaste/","accepts":["Batteries","Paint","Chemicals","Motor oil","Propane tanks","Fluorescent bulbs","Medications"],"hours":"Check website for schedule","notes":"Household Hazardous Waste collection for Mecklenburg County residents."}
  ]
}
